hards/__init__.py
hards/api.py
hards/filesystem.py
hards-1.0.1.dist-info/licenses/LICENCE
hards-1.0.1.dist-info/METADATA
hards-1.0.1.dist-info/WHEEL
hards-1.0.1.dist-info/top_level.txt
hards-1.0.1.dist-info/RECORD
