Metadata-Version: 2.4
Name: hards
Version: 1.0.1
Summary: Extensible interface for managing hierarchical arbitrary data storage.
Author-email: Timothy Nunn <timothy.nunn@ukaea.uk>
Project-URL: Documentation, https://ukaea.github.io/HARDS/
Project-URL: Source, https://github.com/ukaea/HARDS
Keywords: hierarchical data,filesystem,data
Requires-Python: >=3.10
License-File: LICENCE
Provides-Extra: examples
Requires-Dist: seaborn>=0.10; extra == "examples"
Requires-Dist: scipy>=1.10; extra == "examples"
Requires-Dist: pandas; extra == "examples"
Requires-Dist: nbformat>=4.2; extra == "examples"
Requires-Dist: ipython; extra == "examples"
Requires-Dist: ipykernel; extra == "examples"
Provides-Extra: dev
Requires-Dist: ruff==0.11.2; extra == "dev"
Requires-Dist: pre-commit; extra == "dev"
Requires-Dist: pytest; extra == "dev"
Requires-Dist: testbook>=0.4; extra == "dev"
Requires-Dist: Sphinx>=8.0; extra == "dev"
Requires-Dist: nbsphinx>=0.9; extra == "dev"
Requires-Dist: hards[examples]; extra == "dev"
Dynamic: license-file
